odoo10_addon_web_widget_slick-10.0.1.0.0-py2.7-nspkg.pth
odoo/addons/web_widget_slick/README.rst
odoo/addons/web_widget_slick/__init__.py
odoo/addons/web_widget_slick/__manifest__.py
odoo/addons/web_widget_slick/static/description/icon.png
odoo/addons/web_widget_slick/static/description/icon.svg
odoo/addons/web_widget_slick/static/lib/slick/ajax-loader.gif
odoo/addons/web_widget_slick/static/lib/slick/slick-theme.less
odoo/addons/web_widget_slick/static/lib/slick/slick.js
odoo/addons/web_widget_slick/static/lib/slick/slick.less
odoo/addons/web_widget_slick/static/src/js/web_widget_slick.js
odoo/addons/web_widget_slick/static/src/less/slick.less
odoo/addons/web_widget_slick/static/src/xml/web_widget_slick.xml
odoo/addons/web_widget_slick/static/tests/js/web_widget_slick.js
odoo/addons/web_widget_slick/templates/assets.xml
odoo/addons/web_widget_slick/tests/__init__.py
odoo/addons/web_widget_slick/tests/test_ui.py
odoo10_addon_web_widget_slick-10.0.1.0.0.dist-info/DESCRIPTION.rst
odoo10_addon_web_widget_slick-10.0.1.0.0.dist-info/METADATA
odoo10_addon_web_widget_slick-10.0.1.0.0.dist-info/RECORD
odoo10_addon_web_widget_slick-10.0.1.0.0.dist-info/WHEEL
odoo10_addon_web_widget_slick-10.0.1.0.0.dist-info/metadata.json
odoo10_addon_web_widget_slick-10.0.1.0.0.dist-info/namespace_packages.txt
odoo10_addon_web_widget_slick-10.0.1.0.0.dist-info/top_level.txt
